pyautoscene/__init__.py
pyautoscene/ocr.py
pyautoscene/ocr_config.yaml
pyautoscene/references.py
pyautoscene/scene.py
pyautoscene/screen.py
pyautoscene/session.py
pyautoscene/utils.py
pyautoscene-0.2.1.dist-info/METADATA
pyautoscene-0.2.1.dist-info/WHEEL
pyautoscene-0.2.1.dist-info/entry_points.txt
pyautoscene-0.2.1.dist-info/licenses/LICENSE
pyautoscene-0.2.1.dist-info/RECORD
